mapping_united_states/__about__.py
mapping_united_states/__init__.py
mapping_united_states/mapping.py
mapping_united_states-0.0.3.dist-info/METADATA
mapping_united_states-0.0.3.dist-info/WHEEL
mapping_united_states-0.0.3.dist-info/licenses/LICENSE
mapping_united_states-0.0.3.dist-info/RECORD
