Metadata-Version: 2.1
Name: mapping-united-states
Version: 0.0.3
Project-URL: Documentation, https://github.com/unknown/mapping-united-states#readme
Project-URL: Issues, https://github.com/unknown/mapping-united-states/issues
Project-URL: Source, https://github.com/unknown/mapping-united-states
Author-email: "U.N. Owen" <void@some.where>
License-Expression: MIT
License-File: LICENSE
Classifier: Development Status :: 4 - Beta
Classifier: Programming Language :: Python
Classifier: Programming Language :: Python :: 3.7
Classifier: Programming Language :: Python :: 3.8
Classifier: Programming Language :: Python :: 3.9
Classifier: Programming Language :: Python :: 3.10
Classifier: Programming Language :: Python :: 3.11
Classifier: Programming Language :: Python :: Implementation :: CPython
Classifier: Programming Language :: Python :: Implementation :: PyPy
Requires-Python: >=3.7
Requires-Dist: geopandas>=0.12.2
Requires-Dist: matplotlib>=3.6.3
Requires-Dist: pandas>=1.5.3
Requires-Dist: requests>=2.28.2
Requires-Dist: tqdm>=4.64.1
